[
    {
        "dimension": "overworld",
        "id": "church",
        "corner_a": {
            "x": -494,
            "z": 136
        },
        "corner_b": {
            "x": -509,
            "z": 161
        }
    },
    {
        "dimension": "overworld",
        "id": "bloodland",
        "corner_a": {
            "x": -90,
            "z": 511
        },
        "corner_b": {
            "x": -139,
            "z": 617
        }
    },
    {
        "dimension": "overworld",
        "id": "percy_church",
        "corner_a": {
            "x": -304,
            "z": 1873
        },
        "corner_b": {
            "x": -320,
            "z": 1885
        }
    },
    {
        "dimension": "overworld",
        "id": "common_church",
        "corner_a": {
            "x": 1720,
            "z": 375
        },
        "corner_b": {
            "x": 1710,
            "z": 393
        }
    }
]